dfman-0.1.1.dist-info/licenses/LICENSE
dotfile_manager/__init__.py
dotfile_manager/app.py
dotfile_manager/utils.py
dotfile_manager/linker/__init__.py
dotfile_manager/linker/pure.py
dotfile_manager/manifest/concepts.py
dotfile_manager/manifest/diffs.py
dotfile_manager/manifest/loader.py
dotfile_manager/manifest/schema.py
dotfile_manager/syncer/__init__.py
dotfile_manager/syncer/git.py
dfman-0.1.1.dist-info/METADATA
dfman-0.1.1.dist-info/WHEEL
dfman-0.1.1.dist-info/entry_points.txt
dfman-0.1.1.dist-info/top_level.txt
dfman-0.1.1.dist-info/RECORD
