Metadata-Version: 2.4
Name: dfman
Version: 0.1.1
Summary: A tool to manage and synchronize dotfiles across multiple systems.
Requires-Python: >=3.13
License-File: LICENSE
Requires-Dist: cyclopts>=3.19.0
Requires-Dist: escudeiro>=0.2.9
Requires-Dist: gitpython>=3.1.44
Requires-Dist: questionary>=2.1.0
Requires-Dist: ruamel-yaml>=0.18.14
Requires-Dist: termcolor>=3.1.0
Requires-Dist: tomlkit>=0.13.3
Dynamic: license-file
